nsface_cpu/__init__.py
nsface_cpu/bbox_anchor.py
nsface_cpu/get_config.py
nsface_cpu/inference_example.ipynb
nsface_cpu/print_info.py
nsface_cpu/readme.md
nsface_cpu/.ipynb_checkpoints/inference_example-checkpoint.ipynb
nsface_cpu/.ipynb_checkpoints/readme-checkpoint.md
nsface_cpu/__pycache__/__init__.cpython-38.pyc
nsface_cpu/configs/bfm_noneck_v3.pkl
nsface_cpu/configs/param_mean_std_62d_120x120.pkl
nsface_cpu/data/__init__.py
nsface_cpu/data/constant.py
nsface_cpu/data/image.py
nsface_cpu/data/experiments/.DS_Store
nsface_cpu/data/experiments/__init__.py
nsface_cpu/data/experiments/AFLW/__init__.py
nsface_cpu/data/experiments/AFLW/pip_32_16_60_r18_l2_l1_10_1_nb10.py
nsface_cpu/data/experiments/COFW/.DS_Store
nsface_cpu/data/experiments/COFW/__init__.py
nsface_cpu/data/experiments/COFW/pip_32_16_60_r18_l2_l1_10_1_nb10.py
nsface_cpu/data/experiments/WFLW/__init__.py
nsface_cpu/data/experiments/WFLW/pip_32_16_60_mv3_large_l2_l1_10_1_nb10.py
nsface_cpu/data/experiments/WFLW/pip_32_16_60_mv3_small_l2_l1_10_1_nb10.py
nsface_cpu/data/experiments/WFLW/pip_32_16_60_r18_l2_l1_10_1_nb10.py
nsface_cpu/data/experiments/data_300W/__init__.py
nsface_cpu/data/experiments/data_300W/pip_32_16_60_r18_l2_l1_10_1_nb10.py
nsface_cpu/face/README.md
nsface_cpu/face/__init__.py
nsface_cpu/face/blur.py
nsface_cpu/face/common.py
nsface_cpu/face/get_result.py
nsface_cpu/model_zoo/__init__.py
nsface_cpu/model_zoo/get_models.py
nsface_cpu/model_zoo/model_attribute/__init__.py
nsface_cpu/model_zoo/model_attribute/arcface_GenderAge.py
nsface_cpu/model_zoo/model_attribute/arcface_Race.py
nsface_cpu/model_zoo/model_attribute/expression.py
nsface_cpu/model_zoo/model_attribute/liveness.py
nsface_cpu/model_zoo/model_attribute/mask_detector.py
nsface_cpu/model_zoo/model_common/__init__.py
nsface_cpu/model_zoo/model_common/load_onnx.py
nsface_cpu/model_zoo/model_common/load_openvino.py
nsface_cpu/model_zoo/model_detection/__init__.py
nsface_cpu/model_zoo/model_detection/blazeface.py
nsface_cpu_python-1.1.78.dist-info/METADATA
nsface_cpu_python-1.1.78.dist-info/WHEEL
nsface_cpu_python-1.1.78.dist-info/top_level.txt
nsface_cpu_python-1.1.78.dist-info/RECORD
