Metadata-Version: 2.1
Name: nsface-cpu-python
Version: 1.1.78
Summary: Test Face model _ CPU
Home-page: UNKNOWN
Author: minsuny
Author-email: minsun.y@nsensecorp.com
License: UNKNOWN
Platform: UNKNOWN
Requires-Python: >=3
Requires-Dist: onnxruntime
Requires-Dist: openvino (==2022.2.0)
Requires-Dist: scikit-image
Requires-Dist: scikit-learn
Requires-Dist: pillow
Requires-Dist: opencv-python
Requires-Dist: torch
